{
  "books": [
    {
      "id": "1",
      "title": "The Shadow of the Wind",
      "author": "Carlos Ruiz Zafón",
      "genre": "Mystery",
      "publishedYear": 2001
    },
    {
      "id": "2",
      "title": "Gone Girl",
      "author": "Gillian Flynn",
      "genre": "Mystery",
      "publishedYear": 2012
    },
    {
      "id": "3",
      "title": "Big Little Lies",
      "author": "Liane Moriarty",
      "genre": "Mystery",
      "publishedYear": 2014
    },
    {
      "id": "4",
      "title": "Sherlock Holmes: The Complete Novels",
      "author": "Arthur Conan Doyle",
      "genre": "Mystery",
      "publishedYear": 1892
    },
    {
      "id": "5",
      "title": "The Girl with the Dragon Tattoo",
      "author": "Stieg Larsson",
      "genre": "Mystery",
      "publishedYear": 2005
    },
    {
      "id": "6",
      "title": "The Name of the Wind",
      "author": "Patrick Rothfuss",
      "genre": "Fantasy",
      "publishedYear": 2007
    },
    {
      "id": "7",
      "title": "Harry Potter and the Sorcerer's Stone",
      "author": "J.K. Rowling",
      "genre": "Fantasy",
      "publishedYear": 1997
    },
    {
      "id": "8",
      "title": "A Game of Thrones",
      "author": "George R.R. Martin",
      "genre": "Fantasy",
      "publishedYear": 1996
    },
    {
      "id": "9",
      "title": "The Hobbit",
      "author": "J.R.R. Tolkien",
      "genre": "Fantasy",
      "publishedYear": 1937
    },
    {
      "id": "10",
      "title": "The Lion, the Witch and the Wardrobe",
      "author": "C.S. Lewis",
      "genre": "Fantasy",
      "publishedYear": 1950
    },
    {
      "id": "11",
      "title": "To Kill a Mockingbird",
      "author": "Harper Lee",
      "genre": "Classic",
      "publishedYear": 1960
    },
    {
      "id": "12",
      "title": "1984",
      "author": "George Orwell",
      "genre": "Classic",
      "publishedYear": 1949
    },
    {
      "id": "13",
      "title": "Pride and Prejudice",
      "author": "Jane Austen",
      "genre": "Classic",
      "publishedYear": 1813
    },
    {
      "id": "14",
      "title": "The Great Gatsby",
      "author": "F. Scott Fitzgerald",
      "genre": "Classic",
      "publishedYear": 1925
    },
    {
      "id": "15",
      "title": "Moby-Dick",
      "author": "Herman Melville",
      "genre": "Classic",
      "publishedYear": 1851
    },
    {
      "id": "16",
      "title": "The Fault in Our Stars",
      "author": "John Green",
      "genre": "Young Adult",
      "publishedYear": 2012
    },
    {
      "id": "17",
      "title": "Eleanor & Park",
      "author": "Rainbow Rowell",
      "genre": "Young Adult",
      "publishedYear": 2013
    },
    {
      "id": "18",
      "title": "The Hunger Games",
      "author": "Suzanne Collins",
      "genre": "Young Adult",
      "publishedYear": 2008
    },
    {
      "id": "19",
      "title": "Divergent",
      "author": "Veronica Roth",
      "genre": "Young Adult",
      "publishedYear": 2011
    },
    {
      "id": null,
      "title": "Bu seherde kimse yoxdur",
      "author": "Rovsen  Abdullaoglu",
      "genre": "Mystery",
      "publishedYear": 2020
    }
  ]
}